{"line": [{"line": "ज्यां समारोप्य झटिति पूरयामास वीर्यवान्", "result": {"found": false, "syllables": ["ज्यां", "स", "मा", "रो", "प्य", "झ", "टि", "ति", "पू", "र", "या", "मा", "स", "वी", "र्य", "वा", "न्"], "lg": ["ग", "ल", "ग", "ग", "ल", "ल", "ल", "ल", "ग", "ल", "ग", "ग", "ल", "ग", "ल", "ग", ""], "gana": "रभसयजग", "length": 16, "matra": 24, "chanda": [], "jaati": [], "display_scheme": null, "display_line": "ज्यां समारोप्य झटिति पूरयामास वीर्यवान्", "display_syllables": ["ज्यां", "स", "मा", "रो", "प्य", "झ", "टि", "ति", "पू", "र", "या", "मा", "स", "वी", "र्य", "वा", "न्"], "display_lg": ["ग", "ल", "ग", "ग", "ल", "ल", "ल", "ल", "ग", "ल", "ग", "ग", "ल", "ग", "ल", "ग", ""], "display_gana": "रभसयजग", "display_length": 16, "display_matra": 24, "display_chanda": "", "display_jaati": "अष्टिः", "fuzzy": [{"chanda": [["प्रहर्षिणी", [""]]], "gana": "मनजरग", "suggestion": [[["ज्यां"], ["d(स)", "मा", "रो", "प्य"], ["झ", "टि", "ति"], ["पू", "र", "या", "d(मा)", "स"], ["वी", "d(र्य)", "वा", "न्"]]], "cost": 3, "similarity": 0.7692307692307692, "display_chanda": "प्रहर्षिणी"}]}}], "verse": []}