{"line": [{"line": "शत्रुघ्नश्चापि भरतं दृष्ट्वा शोकपरिप्लुतम्", "result": {"found": false, "syllables": ["श", "त्रु", "घ्न", "श्चा", "पि", "भ", "र", "तं", "दृ", "ष्ट्वा", "शो", "क", "प", "रि", "प्लु", "त", "म्"], "lg": ["ग", "ग", "ग", "ग", "ल", "ल", "ल", "ग", "ग", "ग", "ग", "ल", "ल", "ग", "ल", "ग", ""], "gana": "मभयतजग", "length": 16, "matra": 26, "chanda": [], "jaati": [], "display_scheme": null, "display_line": "शत्रुघ्नश्चापि भरतं दृष्ट्वा शोकपरिप्लुतम्", "display_syllables": ["श", "त्रु", "घ्न", "श्चा", "पि", "भ", "र", "तं", "दृ", "ष्ट्वा", "शो", "क", "प", "रि", "प्लु", "त", "म्"], "display_lg": ["ग", "ग", "ग", "ग", "ल", "ल", "ल", "ग", "ग", "ग", "ग", "ल", "ल", "ग", "ल", "ग", ""], "display_gana": "मभयतजग", "display_length": 16, "display_matra": 26, "display_chanda": "", "display_jaati": "अष्टिः", "fuzzy": [{"chanda": [["मदनललिता", [""]]], "gana": "मभनमनग", "suggestion": [[["श", "त्रु", "घ्न", "श्चा", "पि"], ["भ", "र", "i(L)", "r(तं)[L]"], ["दृ", "ष्ट्वा"], ["शो", "क", "प", "d(रि)", "प्लु", "त", "म्"]]], "cost": 3, "similarity": 0.8125, "display_chanda": "मदनललिता"}, {"chanda": [["लोला", [""]], ["मदलेखा", ["1", "2"]]], "gana": "मसमभगग", "suggestion": [[["श", "त्रु", "घ्न", "d(श्चा)", "पि"], ["भ", "r(र)[G]", "तं"], ["दृ", "ष्ट्वा"], ["शो", "क", "प", "रि", "d(प्लु)", "त", "म्"]]], "cost": 3, "similarity": 0.7857142857142857, "display_chanda": "लोला / मदलेखा (पाद 1-2)"}]}}], "verse": []}