{"line": [{"line": "अभिषेचनविघ्नस्य कर्तॄणां ते निवारणे", "result": {"found": true, "syllables": ["अ", "भि", "षे", "च", "न", "वि", "घ्न", "स्य", "क", "र्तॄ", "णां", "ते", "नि", "वा", "र", "णे"], "lg": ["ल", "ल", "ग", "ल", "ल", "ग", "ग", "ल", "ग", "ग", "ग", "ग", "ल", "ग", "ल", "ग"], "gana": "ससरमजग", "length": 16, "matra": 25, "chanda": [["अनुष्टुप्", ["1", "2"]]], "jaati": [], "display_scheme": null, "display_line": "अभिषेचनविघ्नस्य कर्तॄणां ते निवारणे", "display_syllables": ["अ", "भि", "षे", "च", "न", "वि", "घ्न", "स्य", "क", "र्तॄ", "णां", "ते", "नि", "वा", "र", "णे"], "display_lg": ["ल", "ल", "ग", "ल", "ल", "ग", "ग", "ल", "ग", "ग", "ग", "ग", "ल", "ग", "ल", "ग"], "display_gana": "ससरमजग", "display_length": 16, "display_matra": 25, "display_chanda": "अनुष्टुप् (पाद 1-2)", "display_jaati": "अष्टिः", "fuzzy": []}}], "verse": []}