{"line": [{"line": "कथमप्रियमेवाहं ब्रूयां सत्यमिदं वचः", "result": {"found": true, "syllables": ["क", "थ", "म", "प्रि", "य", "मे", "वा", "हं", "ब्रू", "यां", "स", "त्य", "मि", "दं", "व", "चः"], "lg": ["ल", "ल", "ग", "ल", "ल", "ग", "ग", "ग", "ग", "ग", "ग", "ल", "ल", "ग", "ल", "ग"], "gana": "ससमतजग", "length": 16, "matra": 25, "chanda": [["अनुष्टुप्", ["1", "2"]]], "jaati": [], "display_scheme": null, "display_line": "कथमप्रियमेवाहं ब्रूयां सत्यमिदं वचः", "display_syllables": ["क", "थ", "म", "प्रि", "य", "मे", "वा", "हं", "ब्रू", "यां", "स", "त्य", "मि", "दं", "व", "चः"], "display_lg": ["ल", "ल", "ग", "ल", "ल", "ग", "ग", "ग", "ग", "ग", "ग", "ल", "ल", "ग", "ल", "ग"], "display_gana": "ससमतजग", "display_length": 16, "display_matra": 25, "display_chanda": "अनुष्टुप् (पाद 1-2)", "display_jaati": "अष्टिः", "fuzzy": []}}], "verse": []}