{"line": [{"line": "स एष सुमहाकायः कम्पते वाहिनीमुखे", "result": {"found": true, "syllables": ["स", "ए", "ष", "सु", "म", "हा", "का", "यः", "क", "म्प", "ते", "वा", "हि", "नी", "मु", "खे"], "lg": ["ल", "ग", "ल", "ल", "ल", "ग", "ग", "ग", "ग", "ल", "ग", "ग", "ल", "ग", "ल", "ग"], "gana": "जसमयजग", "length": 16, "matra": 25, "chanda": [["अनुष्टुप्", ["1", "2"]]], "jaati": [], "display_scheme": null, "display_line": "स एष सुमहाकायः कम्पते वाहिनीमुखे", "display_syllables": ["स", "ए", "ष", "सु", "म", "हा", "का", "यः", "क", "म्प", "ते", "वा", "हि", "नी", "मु", "खे"], "display_lg": ["ल", "ग", "ल", "ल", "ल", "ग", "ग", "ग", "ग", "ल", "ग", "ग", "ल", "ग", "ल", "ग"], "display_gana": "जसमयजग", "display_length": 16, "display_matra": 25, "display_chanda": "अनुष्टुप् (पाद 1-2)", "display_jaati": "अष्टिः", "fuzzy": []}}], "verse": []}