{"line": [{"line": "ततोऽभ्यवर्षन्त घना दिव्याः कुसुमवृष्टयः", "result": {"found": false, "syllables": ["त", "तो", "ऽ", "भ्य", "व", "र्ष", "न्त", "घ", "ना", "दि", "व्याः", "कु", "सु", "म", "वृ", "ष्ट", "यः"], "lg": ["ल", "ग", "", "ल", "ग", "ग", "ल", "ल", "ग", "ग", "ग", "ल", "ल", "ल", "ग", "ल", "ग"], "gana": "जतयभजग", "length": 16, "matra": 24, "chanda": [], "jaati": [], "display_scheme": null, "display_line": "ततोऽभ्यवर्षन्त घना दिव्याः कुसुमवृष्टयः", "display_syllables": ["त", "तो", "ऽ", "भ्य", "व", "र्ष", "न्त", "घ", "ना", "दि", "व्याः", "कु", "सु", "म", "वृ", "ष्ट", "यः"], "display_lg": ["ल", "ग", "", "ल", "ग", "ग", "ल", "ल", "ग", "ग", "ग", "ल", "ल", "ल", "ग", "ल", "ग"], "display_gana": "जतयभजग", "display_length": 16, "display_matra": 24, "display_chanda": "", "display_jaati": "अष्टिः", "fuzzy": []}}], "verse": []}