{"line": [{"line": "दशकोट्यस्तु सम्पूर्णास्तथैव च नृपात्मज", "result": {"found": true, "syllables": ["द", "श", "को", "ट्य", "स्तु", "स", "म्पू", "र्णा", "स्त", "थै", "व", "च", "नृ", "पा", "त्म", "ज"], "lg": ["ल", "ल", "ग", "ग", "ल", "ग", "ग", "ग", "ल", "ग", "ल", "ल", "ल", "ग", "ल", "ल"], "gana": "सरतभजल", "length": 16, "matra": 23, "chanda": [["अनुष्टुप्", ["1", "2"]]], "jaati": [], "display_scheme": null, "display_line": "दशकोट्यस्तु सम्पूर्णास्तथैव च नृपात्मज", "display_syllables": ["द", "श", "को", "ट्य", "स्तु", "स", "म्पू", "र्णा", "स्त", "थै", "व", "च", "नृ", "पा", "त्म", "ज"], "display_lg": ["ल", "ल", "ग", "ग", "ल", "ग", "ग", "ग", "ल", "ग", "ल", "ल", "ल", "ग", "ल", "ल"], "display_gana": "सरतभजल", "display_length": 16, "display_matra": 23, "display_chanda": "अनुष्टुप् (पाद 1-2)", "display_jaati": "अष्टिः", "fuzzy": []}}], "verse": []}