{"line": [{"line": "भास्करो निष्प्रभश्चैव महर्षेस्तस्य तेजसा", "result": {"found": true, "syllables": ["भा", "स्क", "रो", "नि", "ष्प्र", "भ", "श्चै", "व", "म", "ह", "र्षे", "स्त", "स्य", "ते", "ज", "सा"], "lg": ["ग", "ल", "ग", "ग", "ल", "ग", "ग", "ल", "ल", "ग", "ग", "ग", "ल", "ग", "ल", "ग"], "gana": "ररभमजग", "length": 16, "matra": 26, "chanda": [["अनुष्टुप्", ["1", "2"]]], "jaati": [], "display_scheme": null, "display_line": "भास्करो निष्प्रभश्चैव महर्षेस्तस्य तेजसा", "display_syllables": ["भा", "स्क", "रो", "नि", "ष्प्र", "भ", "श्चै", "व", "म", "ह", "र्षे", "स्त", "स्य", "ते", "ज", "सा"], "display_lg": ["ग", "ल", "ग", "ग", "ल", "ग", "ग", "ल", "ल", "ग", "ग", "ग", "ल", "ग", "ल", "ग"], "display_gana": "ररभमजग", "display_length": 16, "display_matra": 26, "display_chanda": "अनुष्टुप् (पाद 1-2)", "display_jaati": "अष्टिः", "fuzzy": []}}], "verse": []}