{"line": [{"line": "सतुषारावृतां साभ्रां पूर्णचन्द्रप्रभामिव", "result": {"found": true, "syllables": ["स", "तु", "षा", "रा", "वृ", "तां", "सा", "भ्रां", "पू", "र्ण", "च", "न्द्र", "प्र", "भा", "मि", "व"], "lg": ["ल", "ल", "ग", "ग", "ल", "ग", "ग", "ग", "ग", "ल", "ग", "ग", "ल", "ग", "ल", "ल"], "gana": "सरमयजल", "length": 16, "matra": 25, "chanda": [["अनुष्टुप्", ["1", "2"]]], "jaati": [], "display_scheme": null, "display_line": "सतुषारावृतां साभ्रां पूर्णचन्द्रप्रभामिव", "display_syllables": ["स", "तु", "षा", "रा", "वृ", "तां", "सा", "भ्रां", "पू", "र्ण", "च", "न्द्र", "प्र", "भा", "मि", "व"], "display_lg": ["ल", "ल", "ग", "ग", "ल", "ग", "ग", "ग", "ग", "ल", "ग", "ग", "ल", "ग", "ल", "ल"], "display_gana": "सरमयजल", "display_length": 16, "display_matra": 25, "display_chanda": "अनुष्टुप् (पाद 1-2)", "display_jaati": "अष्टिः", "fuzzy": []}}], "verse": []}