{"line": [{"line": "उचितेव प्रवासानां वैदेही प्रतिभाति मे", "result": {"found": true, "syllables": ["उ", "चि", "ते", "व", "प्र", "वा", "सा", "नां", "वै", "दे", "ही", "प्र", "ति", "भा", "ति", "मे"], "lg": ["ल", "ल", "ग", "ग", "ल", "ग", "ग", "ग", "ग", "ग", "ग", "ल", "ल", "ग", "ल", "ग"], "gana": "सरमतजग", "length": 16, "matra": 26, "chanda": [["अनुष्टुप्", ["1", "2"]]], "jaati": [], "display_scheme": null, "display_line": "उचितेव प्रवासानां वैदेही प्रतिभाति मे", "display_syllables": ["उ", "चि", "ते", "व", "प्र", "वा", "सा", "नां", "वै", "दे", "ही", "प्र", "ति", "भा", "ति", "मे"], "display_lg": ["ल", "ल", "ग", "ग", "ल", "ग", "ग", "ग", "ग", "ग", "ग", "ल", "ल", "ग", "ल", "ग"], "display_gana": "सरमतजग", "display_length": 16, "display_matra": 26, "display_chanda": "अनुष्टुप् (पाद 1-2)", "display_jaati": "अष्टिः", "fuzzy": []}}], "verse": []}