{"line": [{"line": "महावीरेन्द्रवरदा राकिण्यम्बास्वरूपिणी", "result": {"found": false, "syllables": ["म", "हा", "वी", "रे", "न्द्र", "व", "र", "दा", "रा", "कि", "ण्य", "म्बा", "स्व", "रू", "पि", "णी"], "lg": ["ल", "ग", "ग", "ग", "ल", "ल", "ल", "ग", "ग", "ग", "ग", "ग", "ल", "ग", "ल", "ग"], "gana": "यभयमजग", "length": 16, "matra": 26, "chanda": [], "jaati": [], "display_scheme": null, "display_line": "महावीरेन्द्रवरदा राकिण्यम्बास्वरूपिणी", "display_syllables": ["म", "हा", "वी", "रे", "न्द्र", "व", "र", "दा", "रा", "कि", "ण्य", "म्बा", "स्व", "रू", "पि", "णी"], "display_lg": ["ल", "ग", "ग", "ग", "ल", "ल", "ल", "ग", "ग", "ग", "ग", "ग", "ल", "ग", "ल", "ग"], "display_gana": "यभयमजग", "display_length": 16, "display_matra": 26, "display_chanda": "", "display_jaati": "अष्टिः", "fuzzy": [{"chanda": [["हंसरुत", ["1", "2"]]], "gana": "मनमतसग", "suggestion": [[["d(म)", "हा", "वी", "रे", "न्द्र", "व", "र", "दा"], ["रा", "कि", "ण्य", "म्बा", "स्व", "r(रू)[L]{रु}", "पि", "i(G)", "i(G)"]]], "cost": 3, "similarity": 0.8125, "display_chanda": "हंसरुत (पाद 1-2)"}]}}], "verse": []}