{"line": [{"line": "शोकेन महताविष्टश्चचाल च मुमोह च", "result": {"found": true, "syllables": ["शो", "के", "न", "म", "ह", "ता", "वि", "ष्ट", "श्च", "चा", "ल", "च", "मु", "मो", "ह", "च"], "lg": ["ग", "ग", "ल", "ल", "ल", "ग", "ग", "ग", "ल", "ग", "ल", "ल", "ल", "ग", "ल", "ल"], "gana": "तसतभजल", "length": 16, "matra": 23, "chanda": [["अनुष्टुप्", ["1", "2"]]], "jaati": [], "display_scheme": null, "display_line": "शोकेन महताविष्टश्चचाल च मुमोह च", "display_syllables": ["शो", "के", "न", "म", "ह", "ता", "वि", "ष्ट", "श्च", "चा", "ल", "च", "मु", "मो", "ह", "च"], "display_lg": ["ग", "ग", "ल", "ल", "ल", "ग", "ग", "ग", "ल", "ग", "ल", "ल", "ल", "ग", "ल", "ल"], "display_gana": "तसतभजल", "display_length": 16, "display_matra": 23, "display_chanda": "अनुष्टुप् (पाद 1-2)", "display_jaati": "अष्टिः", "fuzzy": []}}], "verse": []}