{"line": [{"line": "अद्य नूनं दशरथः सत्त्वमाविश्य भाषते", "result": {"found": false, "syllables": ["अ", "द्य", "नू", "नं", "द", "श", "र", "थः", "स", "त्त्व", "मा", "वि", "श्य", "भा", "ष", "ते"], "lg": ["ग", "ल", "ग", "ग", "ल", "ल", "ल", "ग", "ग", "ल", "ग", "ग", "ल", "ग", "ल", "ग"], "gana": "रभययजग", "length": 16, "matra": 25, "chanda": [], "jaati": [], "display_scheme": null, "display_line": "अद्य नूनं दशरथः सत्त्वमाविश्य भाषते", "display_syllables": ["अ", "द्य", "नू", "नं", "द", "श", "र", "थः", "स", "त्त्व", "मा", "वि", "श्य", "भा", "ष", "ते"], "display_lg": ["ग", "ल", "ग", "ग", "ल", "ल", "ल", "ग", "ग", "ल", "ग", "ग", "ल", "ग", "ल", "ग"], "display_gana": "रभययजग", "display_length": 16, "display_matra": 25, "display_chanda": "", "display_jaati": "अष्टिः", "fuzzy": []}}], "verse": []}