{"line": [{"line": "यथा सूर्यांशुसन्तप्तो हिमवान् प्रसृतो हिमम्", "result": {"found": true, "syllables": ["य", "था", "सू", "र्यां", "शु", "स", "न्त", "प्तो", "हि", "म", "वा", "न्", "प्र", "सृ", "तो", "हि", "म", "म्"], "lg": ["ल", "ग", "ग", "ग", "ल", "ग", "ग", "ग", "ल", "ल", "ग", "", "ल", "ल", "ग", "ल", "ग", ""], "gana": "यरतजजग", "length": 16, "matra": 25, "chanda": [["अनुष्टुप्", ["1", "2"]]], "jaati": [], "display_scheme": null, "display_line": "यथा सूर्यांशुसन्तप्तो हिमवान् प्रसृतो हिमम्", "display_syllables": ["य", "था", "सू", "र्यां", "शु", "स", "न्त", "प्तो", "हि", "म", "वा", "न्", "प्र", "सृ", "तो", "हि", "म", "म्"], "display_lg": ["ल", "ग", "ग", "ग", "ल", "ग", "ग", "ग", "ल", "ल", "ग", "", "ल", "ल", "ग", "ल", "ग", ""], "display_gana": "यरतजजग", "display_length": 16, "display_matra": 25, "display_chanda": "अनुष्टुप् (पाद 1-2)", "display_jaati": "अष्टिः", "fuzzy": []}}], "verse": []}