{"line": [{"line": "यद् देवगर्भप्रतिमे वनं याति न भिद्यते", "result": {"found": false, "syllables": ["य", "द्", "दे", "व", "ग", "र्भ", "प्र", "ति", "मे", "व", "नं", "या", "ति", "न", "भि", "द्य", "ते"], "lg": ["ग", "", "ग", "ल", "ग", "ग", "ल", "ल", "ग", "ल", "ग", "ग", "ल", "ल", "ग", "ल", "ग"], "gana": "ततजतजग", "length": 16, "matra": 25, "chanda": [], "jaati": [], "display_scheme": null, "display_line": "यद् देवगर्भप्रतिमे वनं याति न भिद्यते", "display_syllables": ["य", "द्", "दे", "व", "ग", "र्भ", "प्र", "ति", "मे", "व", "नं", "या", "ति", "न", "भि", "द्य", "ते"], "display_lg": ["ग", "", "ग", "ल", "ग", "ग", "ल", "ल", "ग", "ल", "ग", "ग", "ल", "ल", "ग", "ल", "ग"], "display_gana": "ततजतजग", "display_length": 16, "display_matra": 25, "display_chanda": "", "display_jaati": "अष्टिः", "fuzzy": []}}], "verse": []}