{"line": [{"line": "वसिष्ठो गुणसम्पन्नः शिष्यैः परिवृतस्तथा", "result": {"found": true, "syllables": ["व", "सि", "ष्ठो", "गु", "ण", "स", "म्प", "न्नः", "शि", "ष्यैः", "प", "रि", "वृ", "त", "स्त", "था"], "lg": ["ल", "ग", "ग", "ल", "ल", "ग", "ग", "ग", "ग", "ग", "ल", "ल", "ल", "ग", "ल", "ग"], "gana": "यसमभजग", "length": 16, "matra": 25, "chanda": [["अनुष्टुप्", ["1", "2"]]], "jaati": [], "display_scheme": null, "display_line": "वसिष्ठो गुणसम्पन्नः शिष्यैः परिवृतस्तथा", "display_syllables": ["व", "सि", "ष्ठो", "गु", "ण", "स", "म्प", "न्नः", "शि", "ष्यैः", "प", "रि", "वृ", "त", "स्त", "था"], "display_lg": ["ल", "ग", "ग", "ल", "ल", "ग", "ग", "ग", "ग", "ग", "ल", "ल", "ल", "ग", "ल", "ग"], "display_gana": "यसमभजग", "display_length": 16, "display_matra": 25, "display_chanda": "अनुष्टुप् (पाद 1-2)", "display_jaati": "अष्टिः", "fuzzy": []}}], "verse": []}