{"line": [{"line": "एवमुक्तो महेन्द्रेण त्रिशङ्कुरपतत् पुनः", "result": {"found": true, "syllables": ["ए", "व", "मु", "क्तो", "म", "हे", "न्द्रे", "ण", "त्रि", "श", "ङ्कु", "र", "प", "त", "त्", "पु", "नः"], "lg": ["ग", "ल", "ग", "ग", "ल", "ग", "ग", "ग", "ल", "ग", "ल", "ल", "ल", "ग", "", "ल", "ग"], "gana": "ररतभजग", "length": 16, "matra": 25, "chanda": [["अनुष्टुप्", ["1", "2"]]], "jaati": [], "display_scheme": null, "display_line": "एवमुक्तो महेन्द्रेण त्रिशङ्कुरपतत् पुनः", "display_syllables": ["ए", "व", "मु", "क्तो", "म", "हे", "न्द्रे", "ण", "त्रि", "श", "ङ्कु", "र", "प", "त", "त्", "पु", "नः"], "display_lg": ["ग", "ल", "ग", "ग", "ल", "ग", "ग", "ग", "ल", "ग", "ल", "ल", "ल", "ग", "", "ल", "ग"], "display_gana": "ररतभजग", "display_length": 16, "display_matra": 25, "display_chanda": "अनुष्टुप् (पाद 1-2)", "display_jaati": "अष्टिः", "fuzzy": []}}], "verse": []}