{"line": [{"line": "गवां शतसहस्रं च ब्राह्मणेभ्यो नराधिपः", "result": {"found": true, "syllables": ["ग", "वां", "श", "त", "स", "ह", "स्रं", "च", "ब्रा", "ह्म", "णे", "भ्यो", "न", "रा", "धि", "पः"], "lg": ["ल", "ग", "ल", "ल", "ल", "ग", "ग", "ग", "ग", "ल", "ग", "ग", "ल", "ग", "ल", "ग"], "gana": "जसमयजग", "length": 16, "matra": 25, "chanda": [["अनुष्टुप्", ["1", "2"]]], "jaati": [], "display_scheme": null, "display_line": "गवां शतसहस्रं च ब्राह्मणेभ्यो नराधिपः", "display_syllables": ["ग", "वां", "श", "त", "स", "ह", "स्रं", "च", "ब्रा", "ह्म", "णे", "भ्यो", "न", "रा", "धि", "पः"], "display_lg": ["ल", "ग", "ल", "ल", "ल", "ग", "ग", "ग", "ग", "ल", "ग", "ग", "ल", "ग", "ल", "ग"], "display_gana": "जसमयजग", "display_length": 16, "display_matra": 25, "display_chanda": "अनुष्टुप् (पाद 1-2)", "display_jaati": "अष्टिः", "fuzzy": []}}], "verse": []}