{"line": [{"line": "तं भोगैः सम्परित्यक्तं रामं सम्प्रेक्ष्य मातरः", "result": {"found": true, "syllables": ["तं", "भो", "गैः", "स", "म्प", "रि", "त्य", "क्तं", "रा", "मं", "स", "म्प्रे", "क्ष्य", "मा", "त", "रः"], "lg": ["ग", "ग", "ग", "ग", "ल", "ग", "ग", "ग", "ग", "ग", "ग", "ग", "ल", "ग", "ल", "ग"], "gana": "मरममजग", "length": 16, "matra": 29, "chanda": [["अनुष्टुप्", ["1", "2"]]], "jaati": [], "display_scheme": null, "display_line": "तं भोगैः सम्परित्यक्तं रामं सम्प्रेक्ष्य मातरः", "display_syllables": ["तं", "भो", "गैः", "स", "म्प", "रि", "त्य", "क्तं", "रा", "मं", "स", "म्प्रे", "क्ष्य", "मा", "त", "रः"], "display_lg": ["ग", "ग", "ग", "ग", "ल", "ग", "ग", "ग", "ग", "ग", "ग", "ग", "ल", "ग", "ल", "ग"], "display_gana": "मरममजग", "display_length": 16, "display_matra": 29, "display_chanda": "अनुष्टुप् (पाद 1-2)", "display_jaati": "अष्टिः", "fuzzy": []}}], "verse": []}