{"line": [{"line": "एकान्तमतिरुन्निद्रो गूढो मूढ इवेयते", "result": {"found": true, "syllables": ["ए", "का", "न्त", "म", "ति", "रु", "न्नि", "द्रो", "गू", "ढो", "मू", "ढ", "इ", "वे", "य", "ते"], "lg": ["ग", "ग", "ल", "ल", "ल", "ग", "ग", "ग", "ग", "ग", "ग", "ल", "ल", "ग", "ल", "ग"], "gana": "तसमतजग", "length": 16, "matra": 26, "chanda": [["अनुष्टुप्", ["1", "2"]]], "jaati": [], "display_scheme": null, "display_line": "एकान्तमतिरुन्निद्रो गूढो मूढ इवेयते", "display_syllables": ["ए", "का", "न्त", "म", "ति", "रु", "न्नि", "द्रो", "गू", "ढो", "मू", "ढ", "इ", "वे", "य", "ते"], "display_lg": ["ग", "ग", "ल", "ल", "ल", "ग", "ग", "ग", "ग", "ग", "ग", "ल", "ल", "ग", "ल", "ग"], "display_gana": "तसमतजग", "display_length": 16, "display_matra": 26, "display_chanda": "अनुष्टुप् (पाद 1-2)", "display_jaati": "अष्टिः", "fuzzy": []}}], "verse": []}