{"line": [{"line": "मामेव मातरनिश कलयन्तु मान्ये", "result": {"found": false, "syllables": ["मा", "मे", "व", "मा", "त", "र", "नि", "श", "क", "ल", "य", "न्तु", "मा", "न्ये"], "lg": ["ग", "ग", "ल", "ग", "ल", "ल", "ल", "ल", "ल", "ल", "ग", "ल", "ग", "ग"], "gana": "तभनजगग", "length": 14, "matra": 20, "chanda": [], "jaati": [], "display_scheme": null, "display_line": "मामेव मातरनिश कलयन्तु मान्ये", "display_syllables": ["मा", "मे", "व", "मा", "त", "र", "नि", "श", "क", "ल", "य", "न्तु", "मा", "न्ये"], "display_lg": ["ग", "ग", "ल", "ग", "ल", "ल", "ल", "ल", "ल", "ल", "ग", "ल", "ग", "ग"], "display_gana": "तभनजगग", "display_length": 14, "display_matra": 20, "display_chanda": "", "display_jaati": "शक्वरी", "fuzzy": [{"chanda": [["वसन्ततिलका", [""]], ["सिंहोन्नता", [""]], ["सिंहोद्धता", [""]], ["उद्धर्षिणी", [""]]], "gana": "तभजजगग", "suggestion": [[["मा", "मे", "व"], ["मा", "त", "र", "नि", "r(श)[G]"], ["क", "ल", "य", "न्तु"], ["मा", "न्ये"]]], "cost": 1, "similarity": 0.9285714285714286, "display_chanda": "वसन्ततिलका / सिंहोन्नता / सिंहोद्धता / उद्धर्षिणी"}, {"chanda": [["मध्यक्षामा", [""]], ["कुटिला", [""]], ["हंसश्येनी", [""]]], "gana": "मभनयगग", "suggestion": [[["मा", "मे", "r(व)[G]"], ["मा", "त", "र", "नि", "श"], ["क", "ल", "य", "r(न्तु)[G]{न्तू}"], ["मा", "न्ये"]]], "cost": 2, "similarity": 0.8571428571428572, "display_chanda": "मध्यक्षामा / कुटिला / हंसश्येनी"}, {"chanda": [["प्रहर्षिणी", [""]]], "gana": "मनजरग", "suggestion": [[["मा", "मे", "d(व)"], ["मा", "त", "र", "नि", "श"], ["r(क)[G]", "ल", "य", "न्तु"], ["मा", "न्ये"]]], "cost": 2, "similarity": 0.8461538461538461, "display_chanda": "प्रहर्षिणी"}, {"chanda": [["ऋषभ", [""]]], "gana": "सजससय", "suggestion": [[["i(L)", "r(मा)[L]", "मे", "व"], ["मा", "त", "र", "नि", "r(श)[G]"], ["क", "ल", "य", "न्तु"], ["मा", "न्ये"]]], "cost": 3, "similarity": 0.8, "display_chanda": "ऋषभ"}, {"chanda": [["एला", [""]]], "gana": "सजननय", "suggestion": [[["i(L)", "r(मा)[L]", "मे", "व"], ["मा", "त", "र", "नि", "श"], ["क", "ल", "r(य)[L]", "न्तु"], ["मा", "न्ये"]]], "cost": 3, "similarity": 0.8, "display_chanda": "एला"}, {"chanda": [["असम्बाधा", [""]]], "gana": "मतनसगग", "suggestion": [[["मा", "मे", "r(व)[G]"], ["मा", "i(G)", "d(त)", "र", "नि", "श"], ["क", "ल", "य", "न्तु"], ["मा", "न्ये"]]], "cost": 3, "similarity": 0.7857142857142857, "display_chanda": "असम्बाधा"}, {"chanda": [["चन्द्रौरस", [""]]], "gana": "मभनयलग", "suggestion": [[["मा", "मे", "r(व)[G]"], ["मा", "त", "र", "नि", "श"], ["क", "ल", "य", "i(G)", "d(न्तु)"], ["मा", "न्ये"]]], "cost": 3, "similarity": 0.7857142857142857, "display_chanda": "चन्द्रौरस"}, {"chanda": [["वासन्ती (श)", [""]]], "gana": "मतनयगग", "suggestion": [[["मा", "मे", "r(व)[G]"], ["मा", "r(त)[G]", "र", "नि", "श"], ["क", "ल", "य", "r(न्तु)[G]{न्तू}"], ["मा", "न्ये"]]], "cost": 3, "similarity": 0.7857142857142857, "display_chanda": "वासन्ती (श)"}, {"chanda": [["रुचिरा", [""]], ["प्रभावती", [""]]], "gana": "जभसजग", "suggestion": [[["r(मा)[L]", "मे", "व"], ["मा", "त", "र", "नि", "श"], ["r(क)[G]", "ल", "य", "न्तु"], ["d(मा)", "न्ये"]]], "cost": 3, "similarity": 0.7692307692307692, "display_chanda": "रुचिरा / प्रभावती"}, {"chanda": [["ललिता", [""]]], "gana": "तभजर", "suggestion": [[["मा", "मे", "व"], ["मा", "त", "र", "नि", "r(श)[G]"], ["क", "d(ल)", "य", "न्तु"], ["d(मा)", "न्ये"]]], "cost": 3, "similarity": 0.75, "display_chanda": "ललिता"}]}}], "verse": []}