{"line": [{"line": "धिगस्तु योषितो नाम शठाः स्वार्थपरायणाः", "result": {"found": true, "syllables": ["धि", "ग", "स्तु", "यो", "षि", "तो", "ना", "म", "श", "ठाः", "स्वा", "र्थ", "प", "रा", "य", "णाः"], "lg": ["ल", "ग", "ल", "ग", "ल", "ग", "ग", "ल", "ल", "ग", "ग", "ल", "ल", "ग", "ल", "ग"], "gana": "जरभतजग", "length": 16, "matra": 24, "chanda": [["अनुष्टुप्", ["1", "2"]]], "jaati": [], "display_scheme": null, "display_line": "धिगस्तु योषितो नाम शठाः स्वार्थपरायणाः", "display_syllables": ["धि", "ग", "स्तु", "यो", "षि", "तो", "ना", "म", "श", "ठाः", "स्वा", "र्थ", "प", "रा", "य", "णाः"], "display_lg": ["ल", "ग", "ल", "ग", "ल", "ग", "ग", "ल", "ल", "ग", "ग", "ल", "ल", "ग", "ल", "ग"], "display_gana": "जरभतजग", "display_length": 16, "display_matra": 24, "display_chanda": "अनुष्टुप् (पाद 1-2)", "display_jaati": "अष्टिः", "fuzzy": []}}], "verse": []}