{"line": [{"line": "विश्वगर्भा स्वर्णगर्भाऽवरदा वागधीश्वरी", "result": {"found": false, "syllables": ["वि", "श्व", "ग", "र्भा", "स्व", "र्ण", "ग", "र्भा", "ऽ", "व", "र", "दा", "वा", "ग", "धी", "श्व", "री"], "lg": ["ग", "ल", "ग", "ग", "ग", "ल", "ग", "ग", "", "ल", "ल", "ग", "ग", "ल", "ग", "ल", "ग"], "gana": "रततयजग", "length": 16, "matra": 26, "chanda": [], "jaati": [], "display_scheme": null, "display_line": "विश्वगर्भा स्वर्णगर्भाऽवरदा वागधीश्वरी", "display_syllables": ["वि", "श्व", "ग", "र्भा", "स्व", "र्ण", "ग", "र्भा", "ऽ", "व", "र", "दा", "वा", "ग", "धी", "श्व", "री"], "display_lg": ["ग", "ल", "ग", "ग", "ग", "ल", "ग", "ग", "", "ल", "ल", "ग", "ग", "ल", "ग", "ल", "ग"], "display_gana": "रततयजग", "display_length": 16, "display_matra": 26, "display_chanda": "", "display_jaati": "अष्टिः", "fuzzy": [{"chanda": [["माणवक", ["1", "2"]], ["माणवकक्रीड", ["1", "2"]]], "gana": "भतयसभग", "suggestion": [[["वि", "श्व", "r(ग)[L]", "र्भा"], ["स्व", "र्ण", "i(L)", "d(ग)", "र्भा", "ऽ", "व", "र", "दा"], ["वा", "ग", "धी", "श्व", "री"]]], "cost": 3, "similarity": 0.8125, "display_chanda": "माणवक (पाद 1-2) / माणवकक्रीड (पाद 1-2)"}, {"chanda": [["हंसमाला", ["1", "2"]]], "gana": "सरभतगग", "suggestion": [[["r(वि)[L]", "श्व", "ग", "र्भा"], ["d(स्व)", "र्ण", "ग", "र्भा", "ऽ", "व", "र", "दा"], ["वा", "ग", "धी", "d(श्व)", "री"]]], "cost": 3, "similarity": 0.7857142857142857, "display_chanda": "हंसमाला (पाद 1-2)"}]}}], "verse": []}