{"line": [{"line": "इष्ट्वा देवगणान् सर्वान् विवेशावसथं शुचिः", "result": {"found": true, "syllables": ["इ", "ष्ट्वा", "दे", "व", "ग", "णा", "न्", "स", "र्वा", "न्", "वि", "वे", "शा", "व", "स", "थं", "शु", "चिः"], "lg": ["ग", "ग", "ग", "ल", "ल", "ग", "", "ग", "ग", "", "ल", "ग", "ग", "ल", "ल", "ग", "ल", "ग"], "gana": "मसततजग", "length": 16, "matra": 26, "chanda": [["अनुष्टुप्", ["1", "2"]]], "jaati": [], "display_scheme": null, "display_line": "इष्ट्वा देवगणान् सर्वान् विवेशावसथं शुचिः", "display_syllables": ["इ", "ष्ट्वा", "दे", "व", "ग", "णा", "न्", "स", "र्वा", "न्", "वि", "वे", "शा", "व", "स", "थं", "शु", "चिः"], "display_lg": ["ग", "ग", "ग", "ल", "ल", "ग", "", "ग", "ग", "", "ल", "ग", "ग", "ल", "ल", "ग", "ल", "ग"], "display_gana": "मसततजग", "display_length": 16, "display_matra": 26, "display_chanda": "अनुष्टुप् (पाद 1-2)", "display_jaati": "अष्टिः", "fuzzy": []}}], "verse": []}