{"line": [{"line": "गुहः सन्तापसन्तप्तो राघवं वाक्यमब्रवीत्", "result": {"found": true, "syllables": ["गु", "हः", "स", "न्ता", "प", "स", "न्त", "प्तो", "रा", "घ", "वं", "वा", "क्य", "म", "ब्र", "वी", "त्"], "lg": ["ल", "ग", "ग", "ग", "ल", "ग", "ग", "ग", "ग", "ल", "ग", "ग", "ल", "ग", "ल", "ग", ""], "gana": "यरमयजग", "length": 16, "matra": 27, "chanda": [["अनुष्टुप्", ["1", "2"]]], "jaati": [], "display_scheme": null, "display_line": "गुहः सन्तापसन्तप्तो राघवं वाक्यमब्रवीत्", "display_syllables": ["गु", "हः", "स", "न्ता", "प", "स", "न्त", "प्तो", "रा", "घ", "वं", "वा", "क्य", "म", "ब्र", "वी", "त्"], "display_lg": ["ल", "ग", "ग", "ग", "ल", "ग", "ग", "ग", "ग", "ल", "ग", "ग", "ल", "ग", "ल", "ग", ""], "display_gana": "यरमयजग", "display_length": 16, "display_matra": 27, "display_chanda": "अनुष्टुप् (पाद 1-2)", "display_jaati": "अष्टिः", "fuzzy": []}}], "verse": []}