{"line": [{"line": "इदं द्वितीयं दुर्धर्षं विष्णोर्दत्तं सुरोत्तमैः", "result": {"found": false, "syllables": ["इ", "दं", "द्वि", "ती", "यं", "दु", "र्ध", "र्षं", "वि", "ष्णो", "र्द", "त्तं", "सु", "रो", "त्त", "मैः"], "lg": ["ल", "ग", "ल", "ग", "ग", "ग", "ग", "ग", "ग", "ग", "ग", "ग", "ल", "ग", "ल", "ग"], "gana": "जमममजग", "length": 16, "matra": 28, "chanda": [], "jaati": [], "display_scheme": null, "display_line": "इदं द्वितीयं दुर्धर्षं विष्णोर्दत्तं सुरोत्तमैः", "display_syllables": ["इ", "दं", "द्वि", "ती", "यं", "दु", "र्ध", "र्षं", "वि", "ष्णो", "र्द", "त्तं", "सु", "रो", "त्त", "मैः"], "display_lg": ["ल", "ग", "ल", "ग", "ग", "ग", "ग", "ग", "ग", "ग", "ग", "ग", "ल", "ग", "ल", "ग"], "display_gana": "जमममजग", "display_length": 16, "display_matra": 28, "display_chanda": "", "display_jaati": "अष्टिः", "fuzzy": [{"chanda": [["वक्त्र", ["3", "4"]]], "gana": "ररममयग", "suggestion": [[["d(इ)", "दं"], ["द्वि", "ती", "यं"], ["i(L)", "r(दु)[G]{दू}", "र्ध", "र्षं"], ["वि", "ष्णो", "र्द", "त्तं"], ["सु", "रो", "त्त", "मैः"]]], "cost": 3, "similarity": 0.8125, "display_chanda": "वक्त्र (पाद 3-4)"}]}}], "verse": []}