{"line": [{"line": "ततः परमुवाचेदं वरदं काममोहितम्", "result": {"found": true, "syllables": ["त", "तः", "प", "र", "मु", "वा", "चे", "दं", "व", "र", "दं", "का", "म", "मो", "हि", "त", "म्"], "lg": ["ल", "ग", "ल", "ल", "ल", "ग", "ग", "ग", "ल", "ल", "ग", "ग", "ल", "ग", "ल", "ग", ""], "gana": "जसतयजग", "length": 16, "matra": 24, "chanda": [["अनुष्टुप्", ["1", "2"]]], "jaati": [], "display_scheme": null, "display_line": "ततः परमुवाचेदं वरदं काममोहितम्", "display_syllables": ["त", "तः", "प", "र", "मु", "वा", "चे", "दं", "व", "र", "दं", "का", "म", "मो", "हि", "त", "म्"], "display_lg": ["ल", "ग", "ल", "ल", "ल", "ग", "ग", "ग", "ल", "ल", "ग", "ग", "ल", "ग", "ल", "ग", ""], "display_gana": "जसतयजग", "display_length": 16, "display_matra": 24, "display_chanda": "अनुष्टुप् (पाद 1-2)", "display_jaati": "अष्टिः", "fuzzy": []}}], "verse": []}