{"line": [{"line": "अतिक्रान्तवया राजा मा स्मैनं व्यपरोरुधः", "result": {"found": true, "syllables": ["अ", "ति", "क्रा", "न्त", "व", "या", "रा", "जा", "मा", "स्मै", "नं", "व्य", "प", "रो", "रु", "धः"], "lg": ["ल", "ग", "ग", "ल", "ल", "ग", "ग", "ग", "ग", "ग", "ग", "ल", "ल", "ग", "ल", "ग"], "gana": "यसमतजग", "length": 16, "matra": 26, "chanda": [["अनुष्टुप्", ["1", "2"]]], "jaati": [], "display_scheme": null, "display_line": "अतिक्रान्तवया राजा मा स्मैनं व्यपरोरुधः", "display_syllables": ["अ", "ति", "क्रा", "न्त", "व", "या", "रा", "जा", "मा", "स्मै", "नं", "व्य", "प", "रो", "रु", "धः"], "display_lg": ["ल", "ग", "ग", "ल", "ल", "ग", "ग", "ग", "ग", "ग", "ग", "ल", "ल", "ग", "ल", "ग"], "display_gana": "यसमतजग", "display_length": 16, "display_matra": 26, "display_chanda": "अनुष्टुप् (पाद 1-2)", "display_jaati": "अष्टिः", "fuzzy": []}}], "verse": []}