{"line": [{"line": "प्रवेश्यमानं सत्कृत्य नरेन्द्रेणेन्द्रकर्मणा", "result": {"found": false, "syllables": ["प्र", "वे", "श्य", "मा", "नं", "स", "त्कृ", "त्य", "न", "रे", "न्द्रे", "णे", "न्द्र", "क", "र्म", "णा"], "lg": ["ल", "ग", "ल", "ग", "ग", "ग", "ग", "ल", "ल", "ग", "ग", "ग", "ल", "ग", "ल", "ग"], "gana": "जमभमजग", "length": 16, "matra": 26, "chanda": [], "jaati": [], "display_scheme": null, "display_line": "प्रवेश्यमानं सत्कृत्य नरेन्द्रेणेन्द्रकर्मणा", "display_syllables": ["प्र", "वे", "श्य", "मा", "नं", "स", "त्कृ", "त्य", "न", "रे", "न्द्रे", "णे", "न्द्र", "क", "र्म", "णा"], "display_lg": ["ल", "ग", "ल", "ग", "ग", "ग", "ग", "ल", "ल", "ग", "ग", "ग", "ल", "ग", "ल", "ग"], "display_gana": "जमभमजग", "display_length": 16, "display_matra": 26, "display_chanda": "", "display_jaati": "अष्टिः", "fuzzy": []}}], "verse": []}