{"line": [{"line": "मम माता मुनिश्रेष्ठ रामसन्दर्शनादितः", "result": {"found": true, "syllables": ["म", "म", "मा", "ता", "मु", "नि", "श्रे", "ष्ठ", "रा", "म", "स", "न्द", "र्श", "ना", "दि", "तः"], "lg": ["ल", "ल", "ग", "ग", "ल", "ग", "ग", "ल", "ग", "ल", "ग", "ग", "ल", "ग", "ल", "ग"], "gana": "सररयजग", "length": 16, "matra": 25, "chanda": [["अनुष्टुप्", ["1", "2"]]], "jaati": [], "display_scheme": null, "display_line": "मम माता मुनिश्रेष्ठ रामसन्दर्शनादितः", "display_syllables": ["म", "म", "मा", "ता", "मु", "नि", "श्रे", "ष्ठ", "रा", "म", "स", "न्द", "र्श", "ना", "दि", "तः"], "display_lg": ["ल", "ल", "ग", "ग", "ल", "ग", "ग", "ल", "ग", "ल", "ग", "ग", "ल", "ग", "ल", "ग"], "display_gana": "सररयजग", "display_length": 16, "display_matra": 25, "display_chanda": "अनुष्टुप् (पाद 1-2)", "display_jaati": "अष्टिः", "fuzzy": []}}], "verse": []}