{"line": [{"line": "अद्य यज्ञसमृद्धिर्मे सफला दैवतैः कृता", "result": {"found": true, "syllables": ["अ", "द्य", "य", "ज्ञ", "स", "मृ", "द्धि", "र्मे", "स", "फ", "ला", "दै", "व", "तैः", "कृ", "ता"], "lg": ["ग", "ल", "ग", "ल", "ल", "ग", "ग", "ग", "ल", "ल", "ग", "ग", "ल", "ग", "ल", "ग"], "gana": "रसतयजग", "length": 16, "matra": 25, "chanda": [["अनुष्टुप्", ["1", "2"]]], "jaati": [], "display_scheme": null, "display_line": "अद्य यज्ञसमृद्धिर्मे सफला दैवतैः कृता", "display_syllables": ["अ", "द्य", "य", "ज्ञ", "स", "मृ", "द्धि", "र्मे", "स", "फ", "ला", "दै", "व", "तैः", "कृ", "ता"], "display_lg": ["ग", "ल", "ग", "ल", "ल", "ग", "ग", "ग", "ल", "ल", "ग", "ग", "ल", "ग", "ल", "ग"], "display_gana": "रसतयजग", "display_length": 16, "display_matra": 25, "display_chanda": "अनुष्टुप् (पाद 1-2)", "display_jaati": "अष्टिः", "fuzzy": []}}], "verse": []}