{"line": [{"line": "लक्ष्मणश्चैव धर्मात्मा मन्निदेशे व्यवस्थितः", "result": {"found": true, "syllables": ["ल", "क्ष्म", "ण", "श्चै", "व", "ध", "र्मा", "त्मा", "म", "न्नि", "दे", "शे", "व्य", "व", "स्थि", "तः"], "lg": ["ग", "ल", "ग", "ग", "ल", "ग", "ग", "ग", "ग", "ल", "ग", "ग", "ल", "ग", "ल", "ग"], "gana": "ररमयजग", "length": 16, "matra": 27, "chanda": [["अनुष्टुप्", ["1", "2"]]], "jaati": [], "display_scheme": null, "display_line": "लक्ष्मणश्चैव धर्मात्मा मन्निदेशे व्यवस्थितः", "display_syllables": ["ल", "क्ष्म", "ण", "श्चै", "व", "ध", "र्मा", "त्मा", "म", "न्नि", "दे", "शे", "व्य", "व", "स्थि", "तः"], "display_lg": ["ग", "ल", "ग", "ग", "ल", "ग", "ग", "ग", "ग", "ल", "ग", "ग", "ल", "ग", "ल", "ग"], "display_gana": "ररमयजग", "display_length": 16, "display_matra": 27, "display_chanda": "अनुष्टुप् (पाद 1-2)", "display_jaati": "अष्टिः", "fuzzy": []}}], "verse": []}