{"line": [{"line": "हिरण्यनाभो यत्रास्ते सुतो मे सुमहायशाः", "result": {"found": false, "syllables": ["हि", "र", "ण्य", "ना", "भो", "य", "त्रा", "स्ते", "सु", "तो", "मे", "सु", "म", "हा", "य", "शाः"], "lg": ["ल", "ग", "ल", "ग", "ग", "ग", "ग", "ग", "ल", "ग", "ग", "ल", "ल", "ग", "ल", "ग"], "gana": "जमततजग", "length": 16, "matra": 26, "chanda": [], "jaati": [], "display_scheme": null, "display_line": "हिरण्यनाभो यत्रास्ते सुतो मे सुमहायशाः", "display_syllables": ["हि", "र", "ण्य", "ना", "भो", "य", "त्रा", "स्ते", "सु", "तो", "मे", "सु", "म", "हा", "य", "शाः"], "display_lg": ["ल", "ग", "ल", "ग", "ग", "ग", "ग", "ग", "ल", "ग", "ग", "ल", "ल", "ग", "ल", "ग"], "display_gana": "जमततजग", "display_length": 16, "display_matra": 26, "display_chanda": "", "display_jaati": "अष्टिः", "fuzzy": []}}], "verse": []}