{"line": [{"line": "भरतो दुःखमाचष्टे स्वर्गतिं पृथिवीपतेः", "result": {"found": true, "syllables": ["भ", "र", "तो", "दुः", "ख", "मा", "च", "ष्टे", "स्व", "र्ग", "तिं", "पृ", "थि", "वी", "प", "तेः"], "lg": ["ल", "ल", "ग", "ग", "ल", "ग", "ग", "ग", "ग", "ल", "ग", "ल", "ल", "ग", "ल", "ग"], "gana": "सरमजजग", "length": 16, "matra": 25, "chanda": [["अनुष्टुप्", ["1", "2"]]], "jaati": [], "display_scheme": null, "display_line": "भरतो दुःखमाचष्टे स्वर्गतिं पृथिवीपतेः", "display_syllables": ["भ", "र", "तो", "दुः", "ख", "मा", "च", "ष्टे", "स्व", "र्ग", "तिं", "पृ", "थि", "वी", "प", "तेः"], "display_lg": ["ल", "ल", "ग", "ग", "ल", "ग", "ग", "ग", "ग", "ल", "ग", "ल", "ल", "ग", "ल", "ग"], "display_gana": "सरमजजग", "display_length": 16, "display_matra": 25, "display_chanda": "अनुष्टुप् (पाद 1-2)", "display_jaati": "अष्टिः", "fuzzy": []}}], "verse": []}