{"line": [{"line": "ते हि दुःखमिह प्राप्य विनाशं प्रेत्य लेभिरे", "result": {"found": true, "syllables": ["ते", "हि", "दुः", "ख", "मि", "ह", "प्रा", "प्य", "वि", "ना", "शं", "प्रे", "त्य", "ले", "भि", "रे"], "lg": ["ग", "ल", "ग", "ल", "ल", "ग", "ग", "ल", "ल", "ग", "ग", "ग", "ल", "ग", "ल", "ग"], "gana": "रसभमजग", "length": 16, "matra": 25, "chanda": [["अनुष्टुप्", ["1", "2"]]], "jaati": [], "display_scheme": null, "display_line": "ते हि दुःखमिह प्राप्य विनाशं प्रेत्य लेभिरे", "display_syllables": ["ते", "हि", "दुः", "ख", "मि", "ह", "प्रा", "प्य", "वि", "ना", "शं", "प्रे", "त्य", "ले", "भि", "रे"], "display_lg": ["ग", "ल", "ग", "ल", "ल", "ग", "ग", "ल", "ल", "ग", "ग", "ग", "ल", "ग", "ल", "ग"], "display_gana": "रसभमजग", "display_length": 16, "display_matra": 25, "display_chanda": "अनुष्टुप् (पाद 1-2)", "display_jaati": "अष्टिः", "fuzzy": []}}], "verse": []}