{"line": [{"line": "रुद्रायाप्रतिरूपाय उमां लोकनमस्कृताम्", "result": {"found": true, "syllables": ["रु", "द्रा", "या", "प्र", "ति", "रू", "पा", "य", "उ", "मां", "लो", "क", "न", "म", "स्कृ", "ता", "म्"], "lg": ["ग", "ग", "ग", "ल", "ल", "ग", "ग", "ल", "ल", "ग", "ग", "ल", "ल", "ग", "ल", "ग", ""], "gana": "मसभतजग", "length": 16, "matra": 25, "chanda": [["अनुष्टुप्", ["1", "2"]]], "jaati": [], "display_scheme": null, "display_line": "रुद्रायाप्रतिरूपाय उमां लोकनमस्कृताम्", "display_syllables": ["रु", "द्रा", "या", "प्र", "ति", "रू", "पा", "य", "उ", "मां", "लो", "क", "न", "म", "स्कृ", "ता", "म्"], "display_lg": ["ग", "ग", "ग", "ल", "ल", "ग", "ग", "ल", "ल", "ग", "ग", "ल", "ल", "ग", "ल", "ग", ""], "display_gana": "मसभतजग", "display_length": 16, "display_matra": 25, "display_chanda": "अनुष्टुप् (पाद 1-2)", "display_jaati": "अष्टिः", "fuzzy": []}}], "verse": []}