{"line": [{"line": "श्रेष्ठं ह्यनार्यमेव स्याद् यद् भवानवधार्य माम्", "result": {"found": true, "syllables": ["श्रे", "ष्ठं", "ह्य", "ना", "र्य", "मे", "व", "स्या", "द्", "य", "द्", "भ", "वा", "न", "व", "धा", "र्य", "मा", "म्"], "lg": ["ग", "ग", "ल", "ग", "ल", "ग", "ग", "ग", "", "ग", "", "ल", "ग", "ल", "ल", "ग", "ल", "ग", ""], "gana": "तरमजजग", "length": 16, "matra": 26, "chanda": [["अनुष्टुप्", ["1", "2"]]], "jaati": [], "display_scheme": null, "display_line": "श्रेष्ठं ह्यनार्यमेव स्याद् यद् भवानवधार्य माम्", "display_syllables": ["श्रे", "ष्ठं", "ह्य", "ना", "र्य", "मे", "व", "स्या", "द्", "य", "द्", "भ", "वा", "न", "व", "धा", "र्य", "मा", "म्"], "display_lg": ["ग", "ग", "ल", "ग", "ल", "ग", "ग", "ग", "", "ग", "", "ल", "ग", "ल", "ल", "ग", "ल", "ग", ""], "display_gana": "तरमजजग", "display_length": 16, "display_matra": 26, "display_chanda": "अनुष्टुप् (पाद 1-2)", "display_jaati": "अष्टिः", "fuzzy": []}}], "verse": []}