{"line": [{"line": "इति दुःखाभिसन्तप्तं विलपन्तमचेतनम्", "result": {"found": true, "syllables": ["इ", "ति", "दुः", "खा", "भि", "स", "न्त", "प्तं", "वि", "ल", "प", "न्त", "म", "चे", "त", "न", "म्"], "lg": ["ल", "ल", "ग", "ग", "ल", "ग", "ग", "ग", "ल", "ल", "ग", "ल", "ल", "ग", "ल", "ग", ""], "gana": "सरतजजग", "length": 16, "matra": 24, "chanda": [["अनुष्टुप्", ["1", "2"]]], "jaati": [], "display_scheme": null, "display_line": "इति दुःखाभिसन्तप्तं विलपन्तमचेतनम्", "display_syllables": ["इ", "ति", "दुः", "खा", "भि", "स", "न्त", "प्तं", "वि", "ल", "प", "न्त", "म", "चे", "त", "न", "म्"], "display_lg": ["ल", "ल", "ग", "ग", "ल", "ग", "ग", "ग", "ल", "ल", "ग", "ल", "ल", "ग", "ल", "ग", ""], "display_gana": "सरतजजग", "display_length": 16, "display_matra": 24, "display_chanda": "अनुष्टुप् (पाद 1-2)", "display_jaati": "अष्टिः", "fuzzy": []}}], "verse": []}