{"line": [{"line": "कुशवंशप्रसूतोऽस्मि कौशिको रघुनन्दन", "result": {"found": true, "syllables": ["कु", "श", "वं", "श", "प्र", "सू", "तो", "ऽ", "स्मि", "कौ", "शि", "को", "र", "घु", "न", "न्द", "न"], "lg": ["ल", "ल", "ग", "ग", "ल", "ग", "ग", "", "ल", "ग", "ल", "ग", "ल", "ल", "ग", "ल", "ल"], "gana": "सररजजल", "length": 16, "matra": 23, "chanda": [["अनुष्टुप्", ["1", "2"]]], "jaati": [], "display_scheme": null, "display_line": "कुशवंशप्रसूतोऽस्मि कौशिको रघुनन्दन", "display_syllables": ["कु", "श", "वं", "श", "प्र", "सू", "तो", "ऽ", "स्मि", "कौ", "शि", "को", "र", "घु", "न", "न्द", "न"], "display_lg": ["ल", "ल", "ग", "ग", "ल", "ग", "ग", "", "ल", "ग", "ल", "ग", "ल", "ल", "ग", "ल", "ल"], "display_gana": "सररजजल", "display_length": 16, "display_matra": 23, "display_chanda": "अनुष्टुप् (पाद 1-2)", "display_jaati": "अष्टिः", "fuzzy": []}}], "verse": []}