{"line": [{"line": "ते गत्वा राजभवनं विश्वामित्रमृषिं तदा", "result": {"found": false, "syllables": ["ते", "ग", "त्वा", "रा", "ज", "भ", "व", "नं", "वि", "श्वा", "मि", "त्र", "मृ", "षिं", "त", "दा"], "lg": ["ग", "ग", "ग", "ग", "ल", "ल", "ल", "ग", "ग", "ग", "ग", "ल", "ल", "ग", "ल", "ग"], "gana": "मभयतजग", "length": 16, "matra": 26, "chanda": [], "jaati": [], "display_scheme": null, "display_line": "ते गत्वा राजभवनं विश्वामित्रमृषिं तदा", "display_syllables": ["ते", "ग", "त्वा", "रा", "ज", "भ", "व", "नं", "वि", "श्वा", "मि", "त्र", "मृ", "षिं", "त", "दा"], "display_lg": ["ग", "ग", "ग", "ग", "ल", "ल", "ल", "ग", "ग", "ग", "ग", "ल", "ल", "ग", "ल", "ग"], "display_gana": "मभयतजग", "display_length": 16, "display_matra": 26, "display_chanda": "", "display_jaati": "अष्टिः", "fuzzy": [{"chanda": [["मदनललिता", [""]]], "gana": "मभनमनग", "suggestion": [[["ते"], ["ग", "त्वा"], ["रा", "ज", "भ", "व", "i(L)", "r(नं)[L]"], ["वि", "श्वा", "मि", "त्र", "मृ", "d(षिं)"], ["त", "दा"]]], "cost": 3, "similarity": 0.8125, "display_chanda": "मदनललिता"}, {"chanda": [["लोला", [""]], ["मदलेखा", ["1", "2"]]], "gana": "मसमभगग", "suggestion": [[["ते"], ["ग", "त्वा"], ["d(रा)", "ज", "भ", "r(व)[G]", "नं"], ["वि", "श्वा", "मि", "त्र", "मृ", "षिं"], ["d(त)", "दा"]]], "cost": 3, "similarity": 0.7857142857142857, "display_chanda": "लोला / मदलेखा (पाद 1-2)"}]}}], "verse": []}