{"line": [{"line": "एष विग्रहवान् धर्म एष वीर्यवतां वरः", "result": {"found": true, "syllables": ["ए", "ष", "वि", "ग्र", "ह", "वा", "न्", "ध", "र्म", "ए", "ष", "वी", "र्य", "व", "तां", "व", "रः"], "lg": ["ग", "ल", "ग", "ल", "ल", "ग", "", "ग", "ल", "ग", "ल", "ग", "ल", "ल", "ग", "ल", "ग"], "gana": "रसरजजग", "length": 16, "matra": 24, "chanda": [["अनुष्टुप्", ["1", "2"]]], "jaati": [], "display_scheme": null, "display_line": "एष विग्रहवान् धर्म एष वीर्यवतां वरः", "display_syllables": ["ए", "ष", "वि", "ग्र", "ह", "वा", "न्", "ध", "र्म", "ए", "ष", "वी", "र्य", "व", "तां", "व", "रः"], "display_lg": ["ग", "ल", "ग", "ल", "ल", "ग", "", "ग", "ल", "ग", "ल", "ग", "ल", "ल", "ग", "ल", "ग"], "display_gana": "रसरजजग", "display_length": 16, "display_matra": 24, "display_chanda": "अनुष्टुप् (पाद 1-2)", "display_jaati": "अष्टिः", "fuzzy": []}}], "verse": []}