{"line": [{"line": "राममागतमभ्यर्च्य स्वागतेनागतं मुनिः", "result": {"found": true, "syllables": ["रा", "म", "मा", "ग", "त", "म", "भ्य", "र्च्य", "स्वा", "ग", "ते", "ना", "ग", "तं", "मु", "निः"], "lg": ["ग", "ल", "ग", "ल", "ल", "ग", "ग", "ग", "ग", "ल", "ग", "ग", "ल", "ग", "ल", "ग"], "gana": "रसमयजग", "length": 16, "matra": 26, "chanda": [["अनुष्टुप्", ["1", "2"]]], "jaati": [], "display_scheme": null, "display_line": "राममागतमभ्यर्च्य स्वागतेनागतं मुनिः", "display_syllables": ["रा", "म", "मा", "ग", "त", "म", "भ्य", "र्च्य", "स्वा", "ग", "ते", "ना", "ग", "तं", "मु", "निः"], "display_lg": ["ग", "ल", "ग", "ल", "ल", "ग", "ग", "ग", "ग", "ल", "ग", "ग", "ल", "ग", "ल", "ग"], "display_gana": "रसमयजग", "display_length": 16, "display_matra": 26, "display_chanda": "अनुष्टुप् (पाद 1-2)", "display_jaati": "अष्टिः", "fuzzy": []}}], "verse": []}