{"line": [{"line": "प्लावयत् पूतपाप्मानः स्वर्गं प्राप्ता रघूत्तम", "result": {"found": true, "syllables": ["प्ला", "व", "य", "त्", "पू", "त", "पा", "प्मा", "नः", "स्व", "र्गं", "प्रा", "प्ता", "र", "घू", "त्त", "म"], "lg": ["ग", "ल", "ग", "", "ग", "ल", "ग", "ग", "ग", "ग", "ग", "ग", "ग", "ल", "ग", "ल", "ल"], "gana": "ररममजल", "length": 16, "matra": 27, "chanda": [["अनुष्टुप्", ["1", "2"]]], "jaati": [], "display_scheme": null, "display_line": "प्लावयत् पूतपाप्मानः स्वर्गं प्राप्ता रघूत्तम", "display_syllables": ["प्ला", "व", "य", "त्", "पू", "त", "पा", "प्मा", "नः", "स्व", "र्गं", "प्रा", "प्ता", "र", "घू", "त्त", "म"], "display_lg": ["ग", "ल", "ग", "", "ग", "ल", "ग", "ग", "ग", "ग", "ग", "ग", "ग", "ल", "ग", "ल", "ल"], "display_gana": "ररममजल", "display_length": 16, "display_matra": 27, "display_chanda": "अनुष्टुप् (पाद 1-2)", "display_jaati": "अष्टिः", "fuzzy": []}}], "verse": []}