{"line": [{"line": "पूजितं पुरुषव्याघ्र नातिक्रमितुमर्हसि", "result": {"found": true, "syllables": ["पू", "जि", "तं", "पु", "रु", "ष", "व्या", "घ्र", "ना", "ति", "क्र", "मि", "तु", "म", "र्ह", "सि"], "lg": ["ग", "ल", "ग", "ल", "ल", "ग", "ग", "ल", "ग", "ग", "ल", "ल", "ल", "ग", "ल", "ल"], "gana": "रसरभजल", "length": 16, "matra": 23, "chanda": [["अनुष्टुप्", ["1", "2"]]], "jaati": [], "display_scheme": null, "display_line": "पूजितं पुरुषव्याघ्र नातिक्रमितुमर्हसि", "display_syllables": ["पू", "जि", "तं", "पु", "रु", "ष", "व्या", "घ्र", "ना", "ति", "क्र", "मि", "तु", "म", "र्ह", "सि"], "display_lg": ["ग", "ल", "ग", "ल", "ल", "ग", "ग", "ल", "ग", "ग", "ल", "ल", "ल", "ग", "ल", "ल"], "display_gana": "रसरभजल", "display_length": 16, "display_matra": 23, "display_chanda": "अनुष्टुप् (पाद 1-2)", "display_jaati": "अष्टिः", "fuzzy": []}}], "verse": []}