{"line": [{"line": "प्रिया तु सीता रामस्य दाराः पितृकृता इति", "result": {"found": false, "syllables": ["प्रि", "या", "तु", "सी", "ता", "रा", "म", "स्य", "दा", "राः", "पि", "तृ", "कृ", "ता", "इ", "ति"], "lg": ["ल", "ग", "ल", "ग", "ग", "ग", "ग", "ल", "ग", "ग", "ल", "ल", "ल", "ग", "ल", "ल"], "gana": "जमरभजल", "length": 16, "matra": 24, "chanda": [], "jaati": [], "display_scheme": null, "display_line": "प्रिया तु सीता रामस्य दाराः पितृकृता इति", "display_syllables": ["प्रि", "या", "तु", "सी", "ता", "रा", "म", "स्य", "दा", "राः", "पि", "तृ", "कृ", "ता", "इ", "ति"], "display_lg": ["ल", "ग", "ल", "ग", "ग", "ग", "ग", "ल", "ग", "ग", "ल", "ल", "ल", "ग", "ल", "ल"], "display_gana": "जमरभजल", "display_length": 16, "display_matra": 24, "display_chanda": "", "display_jaati": "अष्टिः", "fuzzy": []}}], "verse": []}