{"line": [{"line": "ऋषिपुत्रास्तु तच्छ्रुत्वा वाक्यं घोराभिसंहितम्", "result": {"found": true, "syllables": ["ऋ", "षि", "पु", "त्रा", "स्तु", "त", "च्छ्रु", "त्वा", "वा", "क्यं", "घो", "रा", "भि", "सं", "हि", "त", "म्"], "lg": ["ल", "ल", "ग", "ग", "ल", "ग", "ग", "ग", "ग", "ग", "ग", "ग", "ल", "ग", "ल", "ग", ""], "gana": "सरममजग", "length": 16, "matra": 27, "chanda": [["अनुष्टुप्", ["1", "2"]]], "jaati": [], "display_scheme": null, "display_line": "ऋषिपुत्रास्तु तच्छ्रुत्वा वाक्यं घोराभिसंहितम्", "display_syllables": ["ऋ", "षि", "पु", "त्रा", "स्तु", "त", "च्छ्रु", "त्वा", "वा", "क्यं", "घो", "रा", "भि", "सं", "हि", "त", "म्"], "display_lg": ["ल", "ल", "ग", "ग", "ल", "ग", "ग", "ग", "ग", "ग", "ग", "ग", "ल", "ग", "ल", "ग", ""], "display_gana": "सरममजग", "display_length": 16, "display_matra": 27, "display_chanda": "अनुष्टुप् (पाद 1-2)", "display_jaati": "अष्टिः", "fuzzy": []}}], "verse": []}