{"line": [{"line": "लोपामुद्रार्चिता लीलाकॢप्तब्रह्माण्डमण्डला", "result": {"found": true, "syllables": ["लो", "पा", "मु", "द्रा", "र्चि", "ता", "ली", "ला", "कॢ", "प्त", "ब्र", "ह्मा", "ण्ड", "म", "ण्ड", "ला"], "lg": ["ग", "ग", "ग", "ग", "ल", "ग", "ग", "ग", "ग", "ग", "ग", "ग", "ल", "ग", "ल", "ग"], "gana": "मरममजग", "length": 16, "matra": 29, "chanda": [["अनुष्टुप्", ["1", "2"]]], "jaati": [], "display_scheme": null, "display_line": "लोपामुद्रार्चिता लीलाकॢप्तब्रह्माण्डमण्डला", "display_syllables": ["लो", "पा", "मु", "द्रा", "र्चि", "ता", "ली", "ला", "कॢ", "प्त", "ब्र", "ह्मा", "ण्ड", "म", "ण्ड", "ला"], "display_lg": ["ग", "ग", "ग", "ग", "ल", "ग", "ग", "ग", "ग", "ग", "ग", "ग", "ल", "ग", "ल", "ग"], "display_gana": "मरममजग", "display_length": 16, "display_matra": 29, "display_chanda": "अनुष्टुप् (पाद 1-2)", "display_jaati": "अष्टिः", "fuzzy": []}}], "verse": []}