{"line": [{"line": "पाणिप्रदानकाले च यत् पुरा त्वग्निसन्निधौ", "result": {"found": true, "syllables": ["पा", "णि", "प्र", "दा", "न", "का", "ले", "च", "य", "त्", "पु", "रा", "त्व", "ग्नि", "स", "न्नि", "धौ"], "lg": ["ग", "ग", "ल", "ग", "ल", "ग", "ग", "ल", "ग", "", "ल", "ग", "ग", "ल", "ग", "ल", "ग"], "gana": "तररयजग", "length": 16, "matra": 26, "chanda": [["अनुष्टुप्", ["1", "2"]]], "jaati": [], "display_scheme": null, "display_line": "पाणिप्रदानकाले च यत् पुरा त्वग्निसन्निधौ", "display_syllables": ["पा", "णि", "प्र", "दा", "न", "का", "ले", "च", "य", "त्", "पु", "रा", "त्व", "ग्नि", "स", "न्नि", "धौ"], "display_lg": ["ग", "ग", "ल", "ग", "ल", "ग", "ग", "ल", "ग", "", "ल", "ग", "ग", "ल", "ग", "ल", "ग"], "display_gana": "तररयजग", "display_length": 16, "display_matra": 26, "display_chanda": "अनुष्टुप् (पाद 1-2)", "display_jaati": "अष्टिः", "fuzzy": []}}], "verse": []}