{"line": [{"line": "दिशः पर्याकुलाः सर्वास्तिमिरेणेव संवृताः", "result": {"found": true, "syllables": ["दि", "शः", "प", "र्या", "कु", "लाः", "स", "र्वा", "स्ति", "मि", "रे", "णे", "व", "सं", "वृ", "ताः"], "lg": ["ल", "ग", "ग", "ग", "ल", "ग", "ग", "ग", "ल", "ल", "ग", "ग", "ल", "ग", "ल", "ग"], "gana": "यरतयजग", "length": 16, "matra": 26, "chanda": [["अनुष्टुप्", ["1", "2"]]], "jaati": [], "display_scheme": null, "display_line": "दिशः पर्याकुलाः सर्वास्तिमिरेणेव संवृताः", "display_syllables": ["दि", "शः", "प", "र्या", "कु", "लाः", "स", "र्वा", "स्ति", "मि", "रे", "णे", "व", "सं", "वृ", "ताः"], "display_lg": ["ल", "ग", "ग", "ग", "ल", "ग", "ग", "ग", "ल", "ल", "ग", "ग", "ल", "ग", "ल", "ग"], "display_gana": "यरतयजग", "display_length": 16, "display_matra": 26, "display_chanda": "अनुष्टुप् (पाद 1-2)", "display_jaati": "अष्टिः", "fuzzy": []}}], "verse": []}