{"line": [{"line": "चतुर्भिर्वेगसम्पन्नैर्हयैः काञ्चनभूषणैः", "result": {"found": true, "syllables": ["च", "तु", "र्भि", "र्वे", "ग", "स", "म्प", "न्नै", "र्ह", "यैः", "का", "ञ्च", "न", "भू", "ष", "णैः"], "lg": ["ल", "ग", "ग", "ग", "ल", "ग", "ग", "ग", "ल", "ग", "ग", "ल", "ल", "ग", "ल", "ग"], "gana": "यरततजग", "length": 16, "matra": 26, "chanda": [["अनुष्टुप्", ["1", "2"]]], "jaati": [], "display_scheme": null, "display_line": "चतुर्भिर्वेगसम्पन्नैर्हयैः काञ्चनभूषणैः", "display_syllables": ["च", "तु", "र्भि", "र्वे", "ग", "स", "म्प", "न्नै", "र्ह", "यैः", "का", "ञ्च", "न", "भू", "ष", "णैः"], "display_lg": ["ल", "ग", "ग", "ग", "ल", "ग", "ग", "ग", "ल", "ग", "ग", "ल", "ल", "ग", "ल", "ग"], "display_gana": "यरततजग", "display_length": 16, "display_matra": 26, "display_chanda": "अनुष्टुप् (पाद 1-2)", "display_jaati": "अष्टिः", "fuzzy": []}}], "verse": []}