{"line": [{"line": "एकसाले स्थाणुमतीं विनते गोमती नदीम्", "result": {"found": false, "syllables": ["ए", "क", "सा", "ले", "स्था", "णु", "म", "तीं", "वि", "न", "ते", "गो", "म", "ती", "न", "दी", "म्"], "lg": ["ग", "ल", "ग", "ग", "ग", "ल", "ल", "ग", "ल", "ल", "ग", "ग", "ल", "ग", "ल", "ग", ""], "gana": "रतजयजग", "length": 16, "matra": 25, "chanda": [], "jaati": [], "display_scheme": null, "display_line": "एकसाले स्थाणुमतीं विनते गोमती नदीम्", "display_syllables": ["ए", "क", "सा", "ले", "स्था", "णु", "म", "तीं", "वि", "न", "ते", "गो", "म", "ती", "न", "दी", "म्"], "display_lg": ["ग", "ल", "ग", "ग", "ग", "ल", "ल", "ग", "ल", "ल", "ग", "ग", "ल", "ग", "ल", "ग", ""], "display_gana": "रतजयजग", "display_length": 16, "display_matra": 25, "display_chanda": "", "display_jaati": "अष्टिः", "fuzzy": [{"chanda": [["माणवक", ["1", "2"]], ["माणवकक्रीड", ["1", "2"]]], "gana": "भतयसभग", "suggestion": [[["ए", "क", "r(सा)[L]", "ले"], ["स्था", "णु", "म", "तीं"], ["i(G)", "d(वि)", "न", "ते"], ["गो", "म", "ती"], ["न", "दी", "म्"]]], "cost": 3, "similarity": 0.8125, "display_chanda": "माणवक (पाद 1-2) / माणवकक्रीड (पाद 1-2)"}]}}], "verse": []}